Metadata-Version: 2.1
Name: fuzzy-matrix-mamdani
Version: 1.1
Summary: matrix and mamdani fuzzy inference
Author-email: epishina.nata@bk.ru
